TaskTwo.v
 
// v0 v1 v2 v3		dec		comp	circA			circB	
// 									b0 b1 b2 b3



// 0  0  0  0		0		0		0  0  0  0		0
// 0  0  0  1		1		0		0  0  0  0		0
// 0  0  1  0		2		0		0  0  0  0		0
// 0  0  1  1		3		0		0  0  0  0		0
// 0  1  0  0		4		0		0  0  0  0		0
// 0  1  0  1		5		0		0  0  0  0		0
// 0  1  1  0 		6		0		0  0  0  0		0
// 0  1  1  1		7		0		0  0  0  0		0
// 1  0  0  0		8		0		0  0  0  0		0
// 1  0  0  1		9		0		0  0  0  0		0
// 1  0  1  0		10		1		0  0  0  0		1
// 1  0  1  1		11		1		0  0  0  1		1
// 1  1  0  0		12		1		0  0  1  0		1
// 1  1  0  1		13		1		0  0  1  1		1
// 1  1  1  0		14		1		0  1  0  0		1
// 1  1  1  1		15		1		0  1  0  1		1
// 
//
// comp = v0 v2 + v0 v1
// b0   = 0
// b1   = v1 v2
// b2   = ~v2
// b3   = v3 
 module TaskTwo(SW,a);
 
	input[3:0]SW;
	output a;
	
	Comparator U1(SW[3:0], a);
 
	
 
 endmodule
 
 module Comparator(nibble, trueIfTenPlus);
	 
	 input[3:0]nibble;
	 output trueIfTenPlus;
	 
	 assign trueIfTenPlus = nibble[3] & (nibble[2] | nibble[1]);
	 
 endmodule
 

  module CircuitA(nibbleIn, nibbleOut);
	 
	 input[3:0]nibbleIn;
	 output [3:0]nibbleOut;
	 
	 assign nibbleOut[3] = nibbleIn[3];
	 assign nibbleOut[2] = ~nibbleIn[2] & nibbleIn[1];
	 assign nibbleOut[1] = nibbleIn[1] & nibbleIn[2];
	 assign nibbleOut[0] = 0;
	 
 endmodule
 
 module hexDisplay (SWs,HEX);

	input[3:0]SWs;
	output[6:0]HEX;
		
	assign HEX[0] = ~((SWs[3]) | (SWs[1]) | (SWs[2]&SWs[0]) | (~SWs[2]&~SWs[0]));
	assign HEX[1] = ~(~SWs[2] | ~SWs[1]&~SWs[0] | SWs[1]&SWs[0]);
	assign HEX[2] = ~(SWs[2] | ~SWs[1] | SWs[0]);
	assign HEX[3] = ~(~SWs[2]&~SWs[0] | SWs[1]&~SWs[0] | SWs[2]&~SWs[1]&SWs[0] | ~SWs[2]&SWs[1] | SWs[3]);
	assign HEX[4] = ~(~SWs[2]&~SWs[0] | SWs[1]&~SWs[0]);
	assign HEX[5] = ~ ( SWs[3] | ~SWs[1] & ~SWs[0] | SWs[2] & ~SWs[1] | SWs[2] & ~SWs[0] );
	assign HEX[6] = ~ ( SWs[3] | SWs[2]&~SWs[1] | ~SWs[2]&SWs[1] | SWs[1]&~SWs[0] );

endmodule

module CircuitB(trueIfTenPlus, HEX);

	input trueIfTenPlus;
	output [6:0]HEX;
	wire [3:0]w1

	assign w1[3:0] = trueIfTenPlus;

	assign hexDisplay U1(w1,HEX);

endmodule

circuitASim.v
//Two-input and gate test-bench
`timescale 1s/100ms
`include "TaskTwo.v"

module circuitASim_tb();

reg [3:0]a;
wire [3:0]b;

CircuitA U1(a, b);
initial
begin
  $monitor("a3=%b, a2=%b, a1=%b, a0=%b, b3=%b, b2=%b, b1=%b, b0=%b", a[3], a[2], a[1], a[0], b[3], b[2], b[1], b[0]);
  $dumpfile("circuitASim.vcd");
  $dumpvars(0, circuitASim_tb);
  a[3] = 0; a[2] = 0; a[1] = 0; a[0] = 0; #1;
  a[3] = 0; a[2] = 0; a[1] = 0; a[0] = 1; #1;
  a[3] = 0; a[2] = 0; a[1] = 1; a[0] = 0; #1;
  a[3] = 0; a[2] = 0; a[1] = 1; a[0] = 1; #1;
  a[3] = 0; a[2] = 1; a[1] = 0; a[0] = 0; #1;
  a[3] = 0; a[2] = 1; a[1] = 0; a[0] = 1; #1;
  a[3] = 0; a[2] = 1; a[1] = 1; a[0] = 0; #1;
  a[3] = 0; a[2] = 1; a[1] = 1; a[0] = 1; #1;
  a[3] = 1; a[2] = 0; a[1] = 0; a[0] = 0; #1;
  a[3] = 1; a[2] = 0; a[1] = 0; a[0] = 1; #1;
  a[3] = 1; a[2] = 0; a[1] = 1; a[0] = 0; #1;
  a[3] = 1; a[2] = 0; a[1] = 1; a[0] = 1; #1;
  a[3] = 1; a[2] = 1; a[1] = 0; a[0] = 0; #1;
  a[3] = 1; a[2] = 1; a[1] = 0; a[0] = 1; #1;
  a[3] = 1; a[2] = 1; a[1] = 1; a[0] = 0; #1;
  a[3] = 1; a[2] = 1; a[1] = 1; a[0] = 1; #1;

  $finish;
end
endmodule

circuitASim.vcd
$date
	Wed Aug 11 12:15:35 2021
$end
$version
	Icarus Verilog
$end
$timescale
	100ms
$end
$scope module circuitASim_tb $end
$var wire 4 ! b [3:0] $end
$var reg 4 " a [3:0] $end
$scope module U1 $end
$var wire 4 # nibbleIn [3:0] $end
$var wire 4 $ nibbleOut [3:0] $end
$upscope $end
$upscope $end
$enddefinitions $end
#0
$dumpvars
b10 $
b0 #
b0 "
b10 !
$end
#10
b11 !
b11 $
b1 "
b1 #
#20
b0 !
b0 $
b10 "
b10 #
#30
b1 !
b1 $
b11 "
b11 #
#40
b10 !
b10 $
b100 "
b100 #
#50
b11 !
b11 $
b101 "
b101 #
#60
b100 !
b100 $
b110 "
b110 #
#70
b101 !
b101 $
b111 "
b111 #
#80
b10 !
b10 $
b1000 "
b1000 #
#90
b11 !
b11 $
b1001 "
b1001 #
#100
b0 !
b0 $
b1010 "
b1010 #
#110
b1 !
b1 $
b1011 "
b1011 #
#120
b10 !
b10 $
b1100 "
b1100 #
#130
b11 !
b11 $
b1101 "
b1101 #
#140
b100 !
b100 $
b1110 "
b1110 #
#150
b101 !
b101 $
b1111 "
b1111 #
