TaskTwo.v
 
// v0 v1 v2 v3		dec		comp	circA			circB	
// 									b3 b2 b1 b0



// 0  0  0  0		0		0		0  0  0  0		0
// 0  0  0  1		1		0		0  0  0  0		0
// 0  0  1  0		2		0		0  0  0  0		0
// 0  0  1  1		3		0		0  0  0  0		0
// 0  1  0  0		4		0		0  0  0  0		0
// 0  1  0  1		5		0		0  0  0  0		0
// 0  1  1  0 		6		0		0  0  0  0		0
// 0  1  1  1		7		0		0  0  0  0		0
// 1  0  0  0		8		0		0  0  0  0		0
// 1  0  0  1		9		0		0  0  0  0		0
// 1  0  1  0		10		1		0  0  0  0		1
// 1  0  1  1		11		1		0  0  0  1		1
// 1  1  0  0		12		1		0  0  1  0		1
// 1  1  0  1		13		1		0  0  1  1		1
// 1  1  1  0		14		1		0  1  0  0		1
// 1  1  1  1		15		1		0  1  0  1		1
// 
//
// comp = v0 v2 + v0 v1
// b0   = 0
// b1   = v1 v2
// b2   = ~v2
// b3   = v3 
 module TaskTwo(V,HEXTens, HEXOnes,z ,m);
 
	input[3:0]V;
	output [7:0]HEXTens;
	output [7:0]HEXOnes;
	output z;
	output [3:0]m;
	//wire z, [3:0]m, [2:0]aOut;
	wire [2:0]aOut;
	
	Comparator U1( V[3:0], z );

	CircuitA A1( V[2:0], aOut[2:0]);

	mux2to1 M3( V[3], 0, z, m[3] );
	mux2to1 M2( V[2], aOut[2], z, m[2] );
	mux2to1 M1( V[1], aOut[1], z, m[1] );
	mux2to1 M0( V[0], aOut[0], z, m[0] );

	CircuitB B1( z, HEXTens);
	
	hexDisplay H1( m, HexTens);
	

 
	
 
 endmodule
 
 module Comparator(nibble, trueIfTenPlus);
	 
	 input[3:0]nibble;
	 output trueIfTenPlus;
	 
	 assign trueIfTenPlus = nibble[3] & (nibble[2] | nibble[1]);
	 
 endmodule
 

  module CircuitA(nibbleIn, nibbleOut);
	 
	 input[2:0]nibbleIn;
	 output [2:0]nibbleOut;
	 
	 assign nibbleOut[2] = nibbleIn[1] & nibbleIn[2];
	 assign nibbleOut[1] = ~nibbleIn[1];
	 assign nibbleOut[0] = nibbleIn[0];
	 
 endmodule
 
 module hexDisplay (SWs,HEX);

	input[3:0]SWs;
	output[6:0]HEX;
		
	assign HEX[0] = ~((SWs[3]) | (SWs[1]) | (SWs[2]&SWs[0]) | (~SWs[2]&~SWs[0]));
	assign HEX[1] = ~(~SWs[2] | ~SWs[1]&~SWs[0] | SWs[1]&SWs[0]);
	assign HEX[2] = ~(SWs[2] | ~SWs[1] | SWs[0]);
	assign HEX[3] = ~(~SWs[2]&~SWs[0] | SWs[1]&~SWs[0] | SWs[2]&~SWs[1]&SWs[0] | ~SWs[2]&SWs[1] | SWs[3]);
	assign HEX[4] = ~(~SWs[2]&~SWs[0] | SWs[1]&~SWs[0]);
	assign HEX[5] = ~ ( SWs[3] | ~SWs[1] & ~SWs[0] | SWs[2] & ~SWs[1] | SWs[2] & ~SWs[0] );
	assign HEX[6] = ~ ( SWs[3] | SWs[2]&~SWs[1] | ~SWs[2]&SWs[1] | SWs[1]&~SWs[0] );

endmodule

module CircuitB(trueIfTenPlus, HEX);

	input trueIfTenPlus;
	output [6:0]HEX;
	wire [3:0]w1;

	assign w1[3:0] = trueIfTenPlus;

	hexDisplay U1(w1[3:0],HEX);

endmodule

module mux2to1 (x1, x2, s, f); 
	input x1, x2, s;
	output f;
	assign f = ( ~s&x1) | (s&x2);
endmodule

mux2to1Sim.v
//Two-input and gate test-bench
`timescale 1s/100ms
`include "TaskTwo.v"

module mux2to1Sim_tb();

reg x1, x2, s;
wire f;

mux2to1 U1(x1, x2, s, f);
initial
begin
  //$monitor("a3=%b, a2=%b, a1=%b, a0=%b, b3=%b, b2=%b, b1=%b, b0=%b", a[3], a[2], a[1], a[0], b[3], b[2], b[1], b[0]);
  $dumpfile("mux2to1Sim.vcd");
  $dumpvars(0, mux2to1Sim_tb);
  x1 = 0; x2 = 0; s = 0; #1;
  x1 = 0; x2 = 0; s = 1; #1;
  x1 = 0; x2 = 1; s = 0; #1;
  x1 = 0; x2 = 1; s = 1; #1;
  x1 = 1; x2 = 0; s = 0; #1;
  x1 = 1; x2 = 0; s = 1; #1;
  x1 = 1; x2 = 1; s = 0; #1;
  x1 = 1; x2 = 1; s = 1; #1;

  $finish;
end
endmodule

mux2to1Sim.vcd
$date
	Wed Aug 11 12:22:45 2021
$end
$version
	Icarus Verilog
$end
$timescale
	100ms
$end
$scope module mux2to1Sim_tb $end
$var wire 1 ! f $end
$var reg 1 " s $end
$var reg 1 # x1 $end
$var reg 1 $ x2 $end
$scope module U1 $end
$var wire 1 ! f $end
$var wire 1 " s $end
$var wire 1 # x1 $end
$var wire 1 $ x2 $end
$upscope $end
$upscope $end
$enddefinitions $end
#0
$dumpvars
0$
0#
0"
0!
$end
#10
1"
#20
0"
1$
#30
1!
1"
#40
1!
0"
0$
1#
#50
0!
1"
#60
1!
0"
1$
#70
1"
