TaskTwo.v
 
// v0 v1 v2 v3		dec		comp	circA			circB	
// 									b0 b1 b2 b3



// 0  0  0  0		0		0		0  0  0  0		0
// 0  0  0  1		1		0		0  0  0  0		0
// 0  0  1  0		2		0		0  0  0  0		0
// 0  0  1  1		3		0		0  0  0  0		0
// 0  1  0  0		4		0		0  0  0  0		0
// 0  1  0  1		5		0		0  0  0  0		0
// 0  1  1  0 		6		0		0  0  0  0		0
// 0  1  1  1		7		0		0  0  0  0		0
// 1  0  0  0		8		0		0  0  0  0		0
// 1  0  0  1		9		0		0  0  0  0		0
// 1  0  1  0		10		1		0  0  0  0		1
// 1  0  1  1		11		1		0  0  0  1		1
// 1  1  0  0		12		1		0  0  1  0		1
// 1  1  0  1		13		1		0  0  1  1		1
// 1  1  1  0		14		1		0  1  0  0		1
// 1  1  1  1		15		1		0  1  0  1		1
// 
//
// comp = v0 v2 + v0 v1
// b0   = 0
// b1   = v1 v2
// b2   = ~v2
// b3   = v3 
 module TaskTwo(SW,a);
 
	input[3:0]SW;
	output a;
	
	Comparator U1(SW[3:0], a);
 
	
 
 endmodule
 
 module Comparator(nibble, trueIfTenPlus);
	 
	 input[3:0]nibble;
	 output trueIfTenPlus;
	 
	 assign trueIfTenPlus = nibble[3] & (nibble[2] | nibble[1]);
	 
 endmodule
 

  module CircuitA(nibbleIn, nibbleOut);
	 
	 input[3:0]nibbleIn;
	 output [3:0]nibbleOut;
	 
	 assign nibbleOut[3] = nibbleIn[3];
	 assign nibbleOut[2] = ~nibbleIn[2];
	 assign nibbleOut[1] = nibbleIn[1] & nibbleIn[2];
	 assign nibbleOut[0] = 0;
	 
 endmodule
 
 module hexDisplay (SWs,HEX);

	input[3:0]SWs;
	output[6:0]HEX;
		
	assign HEX[0] = ~((SWs[3]) | (SWs[1]) | (SWs[2]&SWs[0]) | (~SWs[2]&~SWs[0]));
	assign HEX[1] = ~(~SWs[2] | ~SWs[1]&~SWs[0] | SWs[1]&SWs[0]);
	assign HEX[2] = ~(SWs[2] | ~SWs[1] | SWs[0]);
	assign HEX[3] = ~(~SWs[2]&~SWs[0] | SWs[1]&~SWs[0] | SWs[2]&~SWs[1]&SWs[0] | ~SWs[2]&SWs[1] | SWs[3]);
	assign HEX[4] = ~(~SWs[2]&~SWs[0] | SWs[1]&~SWs[0]);
	assign HEX[5] = ~ ( SWs[3] | ~SWs[1] & ~SWs[0] | SWs[2] & ~SWs[1] | SWs[2] & ~SWs[0] );
	assign HEX[6] = ~ ( SWs[3] | SWs[2]&~SWs[1] | ~SWs[2]&SWs[1] | SWs[1]&~SWs[0] );

endmodule

module CircuitB(trueIfTenPlus, HEX);

	input trueIfTenPlus;
	output [6:0]HEX;
	wire [3:0]w1;

	assign w1[3:0] = trueIfTenPlus;

	hexDisplay U1(w1[3:0],HEX);

endmodule

// module Mux2To1(xIn, s, f);

// 	input [1:0]xIn,s;
// 	output f;
// 	wire w1, w2;

// 	assign w1 = x[0] & ~s;
// 	assign w2 = x[1] & s;
	
// 	assign f  = w1 | w2;

// endmodule

TaskTwoSim.v
//Two-input and gate test-bench
`timescale 1s/100ms
`include "TaskTwo.v"

module TaskTwo_tb();

reg [3:0]a;
wire b;

Comparator iand2(a, b);
initial
begin
  $monitor("a3=%b, a2=%b, a1=%b, a0=%b, b=%b", a[3], a[2], a[1], a[0], b);
  $dumpfile("TaskTwoSim.vcd");
  $dumpvars(0, TaskTwo_tb);
  a[3] = 0; a[2] = 0; a[1] = 0; a[0] = 0; #1;
  a[3] = 0; a[2] = 0; a[1] = 0; a[0] = 1; #1;
  a[3] = 0; a[2] = 0; a[1] = 1; a[0] = 0; #1;
  a[3] = 0; a[2] = 0; a[1] = 1; a[0] = 1; #1;
  a[3] = 0; a[2] = 1; a[1] = 0; a[0] = 0; #1;
  a[3] = 0; a[2] = 1; a[1] = 0; a[0] = 1; #1;
  a[3] = 0; a[2] = 1; a[1] = 1; a[0] = 0; #1;
  a[3] = 0; a[2] = 1; a[1] = 1; a[0] = 1; #1;
  a[3] = 1; a[2] = 0; a[1] = 0; a[0] = 0; #1;
  a[3] = 1; a[2] = 0; a[1] = 0; a[0] = 1; #1;
  a[3] = 1; a[2] = 0; a[1] = 1; a[0] = 0; #1;
  a[3] = 1; a[2] = 0; a[1] = 1; a[0] = 1; #1;
  a[3] = 1; a[2] = 1; a[1] = 0; a[0] = 0; #1;
  a[3] = 1; a[2] = 1; a[1] = 0; a[0] = 1; #1;
  a[3] = 1; a[2] = 1; a[1] = 1; a[0] = 0; #1;
  a[3] = 1; a[2] = 1; a[1] = 1; a[0] = 1; #1;

  $finish;
end
endmodule

TaskTwoSim.vcd
$date
	Wed Aug 11 10:23:42 2021
$end
$version
	Icarus Verilog
$end
$timescale
	100ms
$end
$scope module TaskTwo_tb $end
$var wire 1 ! b $end
$var reg 4 " a [3:0] $end
$scope module iand2 $end
$var wire 4 # nibble [3:0] $end
$var wire 1 ! trueIfTenPlus $end
$upscope $end
$upscope $end
$enddefinitions $end
#0
$dumpvars
b0 #
b0 "
0!
$end
#10
b1 "
b1 #
#20
b10 "
b10 #
#30
b11 "
b11 #
#40
b100 "
b100 #
#50
b101 "
b101 #
#60
b110 "
b110 #
#70
b111 "
b111 #
#80
0!
b1000 "
b1000 #
#90
b1001 "
b1001 #
#100
1!
b1010 "
b1010 #
#110
b1011 "
b1011 #
#120
b1100 "
b1100 #
#130
b1101 "
b1101 #
#140
b1110 "
b1110 #
#150
b1111 "
b1111 #
